{
    "title": "Quick Pickled Cucumber",
    "quantity": {
        "number": "?",
        "dimensions": [],
        "label": ""
    },
    "source": null,
    "ingredient_list": [
        {
            "text": "250ml rice wine vinegar (also worked fine with cheap white vinegar)",
            "optional": false,
            "alternative_ingredients": [],
            "note": null,
            "type": "INGREDIENT"
        },
        {
            "text": "250ml water",
            "optional": false,
            "alternative_ingredients": [],
            "note": null,
            "type": "INGREDIENT"
        },
        {
            "text": "150g sugar",
            "optional": false,
            "alternative_ingredients": [],
            "note": null,
            "type": "INGREDIENT"
        },
        {
            "text": "1 tablespoon course salt",
            "optional": false,
            "alternative_ingredients": [],
            "note": null,
            "type": "INGREDIENT"
        },
        {
            "text": "1 Cucumber",
            "optional": false,
            "alternative_ingredients": [],
            "note": null,
            "type": "INGREDIENT"
        }
    ],
    "method": [
        {
            "text": "Heat everything up except the cucumber, until everything dissolves",
            "post_notes": [],
            "pre_notes": [],
            "type": "METHOD_STEP"
        },
        {
            "text": "Finely slice the cucumber, and add it to the pickle liquid",
            "post_notes": [],
            "pre_notes": [],
            "type": "METHOD_STEP"
        },
        {
            "text": "Strain away the liquid after 10 minutes",
            "post_notes": [],
            "pre_notes": [],
            "type": "METHOD_STEP"
        }
    ],
    "notes": [
        {
            "text": "Good with carrots too",
            "note_type": null
        }
    ],
    "serving_suggestions": null,
    "variations": null,
    "attempt_log": null
}